{"match_id":"b653627e-fd55-491c-bfa3-7bace74c3ea6","map":"Baltic_Main","map_name":"Erangel","created_at":"2026-06-05T19:37:56Z","duration_s":1392,"match_stats":{"D282":{"placement":48,"damage":0,"kills":0,"survival_s":117},"S821":{"placement":48,"damage":0,"kills":0,"survival_s":117}},"positions":{"D282":[{"t":0,"x":798055,"y":19112,"hp":100,"blue":false,"dbno":false},{"t":0,"x":798055,"y":19112,"hp":100,"blue":false,"dbno":false},{"t":0,"x":797753,"y":20137,"hp":100,"blue":false,"dbno":false},{"t":0,"x":794233,"y":23644,"hp":100,"blue":false,"dbno":false},{"t":0,"x":792481,"y":25855,"hp":100,"blue":false,"dbno":false},{"t":0,"x":790189,"y":28732,"hp":100,"blue":false,"dbno":false},{"t":6,"x":-3020,"y":691164,"hp":100,"blue":false,"dbno":false},{"t":15,"x":109340,"y":601218,"hp":100,"blue":false,"dbno":false},{"t":25,"x":221686,"y":511283,"hp":100,"blue":false,"dbno":false},{"t":35,"x":226072,"y":472659,"hp":100,"blue":false,"dbno":false},{"t":45,"x":222070,"y":430014,"hp":100,"blue":false,"dbno":false},{"t":55,"x":220138,"y":407924,"hp":100,"blue":false,"dbno":false},{"t":64,"x":219308,"y":395559,"hp":100,"blue":false,"dbno":false},{"t":74,"x":216396,"y":393997,"hp":100,"blue":false,"dbno":false},{"t":83,"x":215791,"y":393685,"hp":100,"blue":false,"dbno":false},{"t":92,"x":216488,"y":392941,"hp":100,"blue":false,"dbno":false},{"t":102,"x":216263,"y":393508,"hp":100,"blue":false,"dbno":false},{"t":112,"x":216185,"y":393282,"hp":100,"blue":false,"dbno":false},{"t":121,"x":216031,"y":393291,"hp":0,"blue":false,"dbno":false}],"S821":[{"t":0,"x":798167,"y":19920,"hp":100,"blue":false,"dbno":false},{"t":0,"x":798168,"y":19920,"hp":100,"blue":false,"dbno":false},{"t":0,"x":798168,"y":19920,"hp":100,"blue":false,"dbno":false},{"t":0,"x":798168,"y":19920,"hp":100,"blue":false,"dbno":false},{"t":0,"x":798168,"y":19920,"hp":100,"blue":false,"dbno":false},{"t":0,"x":798168,"y":19920,"hp":100,"blue":false,"dbno":false},{"t":2,"x":-47655,"y":726894,"hp":100,"blue":false,"dbno":false},{"t":12,"x":65131,"y":636608,"hp":100,"blue":false,"dbno":false},{"t":22,"x":177371,"y":546757,"hp":100,"blue":false,"dbno":false},{"t":31,"x":255648,"y":478303,"hp":100,"blue":false,"dbno":false},{"t":41,"x":239347,"y":443507,"hp":100,"blue":false,"dbno":false},{"t":51,"x":223681,"y":412731,"hp":100,"blue":false,"dbno":false},{"t":60,"x":218951,"y":404266,"hp":100,"blue":false,"dbno":false},{"t":70,"x":216241,"y":396839,"hp":100,"blue":false,"dbno":false},{"t":79,"x":218658,"y":397451,"hp":0,"blue":false,"dbno":true},{"t":89,"x":218813,"y":397341,"hp":0,"blue":false,"dbno":true},{"t":98,"x":218813,"y":397341,"hp":0,"blue":false,"dbno":true},{"t":108,"x":218839,"y":397341,"hp":0,"blue":false,"dbno":true}]},"circles":[{"t":10,"safe_x":408000,"safe_y":408000,"safe_r":581999,"warn_x":0,"warn_y":0,"warn_r":0},{"t":20,"safe_x":408000,"safe_y":408000,"safe_r":581999,"warn_x":0,"warn_y":0,"warn_r":0},{"t":29,"safe_x":408000,"safe_y":408000,"safe_r":581999,"warn_x":0,"warn_y":0,"warn_r":0},{"t":39,"safe_x":408000,"safe_y":408000,"safe_r":581999,"warn_x":0,"warn_y":0,"warn_r":0},{"t":49,"safe_x":408000,"safe_y":408000,"safe_r":581999,"warn_x":0,"warn_y":0,"warn_r":0},{"t":59,"safe_x":408000,"safe_y":408000,"safe_r":581999,"warn_x":0,"warn_y":0,"warn_r":0},{"t":68,"safe_x":408000,"safe_y":408000,"safe_r":581999,"warn_x":0,"warn_y":0,"warn_r":0},{"t":77,"safe_x":408000,"safe_y":408000,"safe_r":581999,"warn_x":0,"warn_y":0,"warn_r":0},{"t":87,"safe_x":408000,"safe_y":408000,"safe_r":581999,"warn_x":0,"warn_y":0,"warn_r":0},{"t":96,"safe_x":408000,"safe_y":408000,"safe_r":581999,"warn_x":174689,"warn_y":568151,"warn_r":203700},{"t":106,"safe_x":408000,"safe_y":408000,"safe_r":581999,"warn_x":174689,"warn_y":568151,"warn_r":203700},{"t":116,"safe_x":408000,"safe_y":408000,"safe_r":581999,"warn_x":174689,"warn_y":568151,"warn_r":203700},{"t":125,"safe_x":408000,"safe_y":408000,"safe_r":581999,"warn_x":174689,"warn_y":568151,"warn_r":203700},{"t":135,"safe_x":408000,"safe_y":408000,"safe_r":581999,"warn_x":174689,"warn_y":568151,"warn_r":203700},{"t":144,"safe_x":408000,"safe_y":408000,"safe_r":581999,"warn_x":174689,"warn_y":568151,"warn_r":203700},{"t":154,"safe_x":408000,"safe_y":408000,"safe_r":581999,"warn_x":174689,"warn_y":568151,"warn_r":203700},{"t":164,"safe_x":408000,"safe_y":408000,"safe_r":581999,"warn_x":174689,"warn_y":568151,"warn_r":203700},{"t":173,"safe_x":408000,"safe_y":408000,"safe_r":581999,"warn_x":174689,"warn_y":568151,"warn_r":203700},{"t":183,"safe_x":408000,"safe_y":408000,"safe_r":581999,"warn_x":174689,"warn_y":568151,"warn_r":203700},{"t":193,"safe_x":408000,"safe_y":408000,"safe_r":581999,"warn_x":174689,"warn_y":568151,"warn_r":203700},{"t":202,"safe_x":408000,"safe_y":408000,"safe_r":581999,"warn_x":174689,"warn_y":568151,"warn_r":203700},{"t":212,"safe_x":408000,"safe_y":408000,"safe_r":581999,"warn_x":174689,"warn_y":568151,"warn_r":203700},{"t":222,"safe_x":408000,"safe_y":408000,"safe_r":581999,"warn_x":174689,"warn_y":568151,"warn_r":203700},{"t":232,"safe_x":408000,"safe_y":408000,"safe_r":581999,"warn_x":174689,"warn_y":568151,"warn_r":203700},{"t":242,"safe_x":408000,"safe_y":408000,"safe_r":581999,"warn_x":174689,"warn_y":568151,"warn_r":203700},{"t":251,"safe_x":408000,"safe_y":408000,"safe_r":581999,"warn_x":174689,"warn_y":568151,"warn_r":203700},{"t":261,"safe_x":408000,"safe_y":408000,"safe_r":581999,"warn_x":174689,"warn_y":568151,"warn_r":203700},{"t":271,"safe_x":408000,"safe_y":408000,"safe_r":581999,"warn_x":174689,"warn_y":568151,"warn_r":203700},{"t":281,"safe_x":408000,"safe_y":408000,"safe_r":581999,"warn_x":174689,"warn_y":568151,"warn_r":203700},{"t":291,"safe_x":408000,"safe_y":408000,"safe_r":581999,"warn_x":174689,"warn_y":568151,"warn_r":203700},{"t":301,"safe_x":408000,"safe_y":408000,"safe_r":581999,"warn_x":174689,"warn_y":568151,"warn_r":203700},{"t":310,"safe_x":408000,"safe_y":408000,"safe_r":581999,"warn_x":174689,"warn_y":568151,"warn_r":203700},{"t":320,"safe_x":408000,"safe_y":408000,"safe_r":581999,"warn_x":174689,"warn_y":568151,"warn_r":203700},{"t":330,"safe_x":399335,"safe_y":413948,"safe_r":567950,"warn_x":174689,"warn_y":568151,"warn_r":203700},{"t":340,"safe_x":390700,"safe_y":419875,"safe_r":553948,"warn_x":174689,"warn_y":568151,"warn_r":203700},{"t":350,"safe_x":382078,"safe_y":425794,"safe_r":539968,"warn_x":174689,"warn_y":568151,"warn_r":203700},{"t":360,"safe_x":373420,"safe_y":431736,"safe_r":525930,"warn_x":174689,"warn_y":568151,"warn_r":203700},{"t":369,"safe_x":364803,"safe_y":437651,"safe_r":511958,"warn_x":174689,"warn_y":568151,"warn_r":203700},{"t":379,"safe_x":356156,"safe_y":443587,"safe_r":497938,"warn_x":174689,"warn_y":568151,"warn_r":203700},{"t":389,"safe_x":347524,"safe_y":449512,"safe_r":483942,"warn_x":174689,"warn_y":568151,"warn_r":203700},{"t":399,"safe_x":338877,"safe_y":455448,"safe_r":469920,"warn_x":174689,"warn_y":568151,"warn_r":203700},{"t":409,"safe_x":330237,"safe_y":461378,"safe_r":455912,"warn_x":174689,"warn_y":568151,"warn_r":203700},{"t":419,"safe_x":321581,"safe_y":467320,"safe_r":441876,"warn_x":174689,"warn_y":568151,"warn_r":203700},{"t":429,"safe_x":312956,"safe_y":473241,"safe_r":427891,"warn_x":174689,"warn_y":568151,"warn_r":203700},{"t":439,"safe_x":304325,"safe_y":479165,"safe_r":413896,"warn_x":174689,"warn_y":568151,"warn_r":203700},{"t":449,"safe_x":295664,"safe_y":485110,"safe_r":399854,"warn_x":174689,"warn_y":568151,"warn_r":203700},{"t":459,"safe_x":287039,"safe_y":491030,"safe_r":385869,"warn_x":174689,"warn_y":568151,"warn_r":203700},{"t":469,"safe_x":278390,"safe_y":496968,"safe_r":371844,"warn_x":174689,"warn_y":568151,"warn_r":203700},{"t":479,"safe_x":269748,"safe_y":502899,"safe_r":357833,"warn_x":174689,"warn_y":568151,"warn_r":203700},{"t":488,"safe_x":261107,"safe_y":508831,"safe_r":343821,"warn_x":174689,"warn_y":568151,"warn_r":203700},{"t":498,"safe_x":252478,"safe_y":514754,"safe_r":329830,"warn_x":174689,"warn_y":568151,"warn_r":203700},{"t":508,"safe_x":243840,"safe_y":520683,"safe_r":315824,"warn_x":174689,"warn_y":568151,"warn_r":203700},{"t":518,"safe_x":235193,"safe_y":526619,"safe_r":301803,"warn_x":174689,"warn_y":568151,"warn_r":203700},{"t":528,"safe_x":226563,"safe_y":532543,"safe_r":287810,"warn_x":174689,"warn_y":568151,"warn_r":203700},{"t":538,"safe_x":217933,"safe_y":538467,"safe_r":273818,"warn_x":174689,"warn_y":568151,"warn_r":203700},{"t":548,"safe_x":209296,"safe_y":544395,"safe_r":259813,"warn_x":174689,"warn_y":568151,"warn_r":203700},{"t":558,"safe_x":200654,"safe_y":550327,"safe_r":245801,"warn_x":174689,"warn_y":568151,"warn_r":203700},{"t":568,"safe_x":192007,"safe_y":556263,"safe_r":231780,"warn_x":174689,"warn_y":568151,"warn_r":203700},{"t":578,"safe_x":183362,"safe_y":562197,"safe_r":217763,"warn_x":174689,"warn_y":568151,"warn_r":203700},{"t":587,"safe_x":174744,"safe_y":568112,"safe_r":203790,"warn_x":174689,"warn_y":568151,"warn_r":203700},{"t":597,"safe_x":174689,"safe_y":568151,"safe_r":203700,"warn_x":164789,"warn_y":574685,"warn_r":112035},{"t":607,"safe_x":174689,"safe_y":568151,"safe_r":203700,"warn_x":164789,"warn_y":574685,"warn_r":112035},{"t":617,"safe_x":174689,"safe_y":568151,"safe_r":203700,"warn_x":164789,"warn_y":574685,"warn_r":112035},{"t":627,"safe_x":174689,"safe_y":568151,"safe_r":203700,"warn_x":164789,"warn_y":574685,"warn_r":112035},{"t":637,"safe_x":174689,"safe_y":568151,"safe_r":203700,"warn_x":164789,"warn_y":574685,"warn_r":112035},{"t":647,"safe_x":174689,"safe_y":568151,"safe_r":203700,"warn_x":164789,"warn_y":574685,"warn_r":112035},{"t":657,"safe_x":174689,"safe_y":568151,"safe_r":203700,"warn_x":164789,"warn_y":574685,"warn_r":112035},{"t":667,"safe_x":174689,"safe_y":568151,"safe_r":203700,"warn_x":164789,"warn_y":574685,"warn_r":112035},{"t":677,"safe_x":174689,"safe_y":568151,"safe_r":203700,"warn_x":164789,"warn_y":574685,"warn_r":112035},{"t":687,"safe_x":174689,"safe_y":568151,"safe_r":203700,"warn_x":164789,"warn_y":574685,"warn_r":112035},{"t":697,"safe_x":174689,"safe_y":568151,"safe_r":203700,"warn_x":164789,"warn_y":574685,"warn_r":112035},{"t":707,"safe_x":174689,"safe_y":568151,"safe_r":203700,"warn_x":164789,"warn_y":574685,"warn_r":112035},{"t":717,"safe_x":173600,"safe_y":568869,"safe_r":193618,"warn_x":164789,"warn_y":574685,"warn_r":112035},{"t":727,"safe_x":172501,"safe_y":569594,"safe_r":183447,"warn_x":164789,"warn_y":574685,"warn_r":112035},{"t":737,"safe_x":171399,"safe_y":570322,"safe_r":173239,"warn_x":164789,"warn_y":574685,"warn_r":112035},{"t":747,"safe_x":170300,"safe_y":571047,"safe_r":163066,"warn_x":164789,"warn_y":574685,"warn_r":112035},{"t":757,"safe_x":169202,"safe_y":571772,"safe_r":152897,"warn_x":164789,"warn_y":574685,"warn_r":112035},{"t":767,"safe_x":168103,"safe_y":572497,"safe_r":142722,"warn_x":164789,"warn_y":574685,"warn_r":112035},{"t":776,"safe_x":167003,"safe_y":573223,"safe_r":132541,"warn_x":164789,"warn_y":574685,"warn_r":112035},{"t":786,"safe_x":165903,"safe_y":573949,"safe_r":122351,"warn_x":164789,"warn_y":574685,"warn_r":112035},{"t":796,"safe_x":164802,"safe_y":574676,"safe_r":112154,"warn_x":164789,"warn_y":574685,"warn_r":112035},{"t":806,"safe_x":164789,"safe_y":574685,"safe_r":112035,"warn_x":154032,"warn_y":582463,"warn_r":67221},{"t":816,"safe_x":164789,"safe_y":574685,"safe_r":112035,"warn_x":154032,"warn_y":582463,"warn_r":67221},{"t":826,"safe_x":164789,"safe_y":574685,"safe_r":112035,"warn_x":154032,"warn_y":582463,"warn_r":67221},{"t":836,"safe_x":164789,"safe_y":574685,"safe_r":112035,"warn_x":154032,"warn_y":582463,"warn_r":67221},{"t":846,"safe_x":164789,"safe_y":574685,"safe_r":112035,"warn_x":154032,"warn_y":582463,"warn_r":67221},{"t":856,"safe_x":164789,"safe_y":574685,"safe_r":112035,"warn_x":154032,"warn_y":582463,"warn_r":67221},{"t":866,"safe_x":164789,"safe_y":574685,"safe_r":112035,"warn_x":154032,"warn_y":582463,"warn_r":67221},{"t":876,"safe_x":164789,"safe_y":574685,"safe_r":112035,"warn_x":154032,"warn_y":582463,"warn_r":67221},{"t":886,"safe_x":164789,"safe_y":574685,"safe_r":112035,"warn_x":154032,"warn_y":582463,"warn_r":67221},{"t":896,"safe_x":164789,"safe_y":574685,"safe_r":112035,"warn_x":154032,"warn_y":582463,"warn_r":67221},{"t":906,"safe_x":163465,"safe_y":575642,"safe_r":106520,"warn_x":154032,"warn_y":582463,"warn_r":67221},{"t":916,"safe_x":162122,"safe_y":576613,"safe_r":100925,"warn_x":154032,"warn_y":582463,"warn_r":67221},{"t":926,"safe_x":160777,"safe_y":577586,"safe_r":95322,"warn_x":154032,"warn_y":582463,"warn_r":67221},{"t":936,"safe_x":159433,"safe_y":578557,"safe_r":89725,"warn_x":154032,"warn_y":582463,"warn_r":67221},{"t":946,"safe_x":158088,"safe_y":579530,"safe_r":84121,"warn_x":154032,"warn_y":582463,"warn_r":67221},{"t":956,"safe_x":156744,"safe_y":580502,"safe_r":78521,"warn_x":154032,"warn_y":582463,"warn_r":67221},{"t":966,"safe_x":155401,"safe_y":581473,"safe_r":72924,"warn_x":154032,"warn_y":582463,"warn_r":67221},{"t":976,"safe_x":154056,"safe_y":582446,"safe_r":67322,"warn_x":154032,"warn_y":582463,"warn_r":67221},{"t":985,"safe_x":154032,"safe_y":582463,"safe_r":67221,"warn_x":150183,"warn_y":561919,"warn_r":36971},{"t":995,"safe_x":154032,"safe_y":582463,"safe_r":67221,"warn_x":150183,"warn_y":561919,"warn_r":36971},{"t":1005,"safe_x":154032,"safe_y":582463,"safe_r":67221,"warn_x":150183,"warn_y":561919,"warn_r":36971},{"t":1015,"safe_x":154032,"safe_y":582463,"safe_r":67221,"warn_x":150183,"warn_y":561919,"warn_r":36971},{"t":1025,"safe_x":154032,"safe_y":582463,"safe_r":67221,"warn_x":150183,"warn_y":561919,"warn_r":36971},{"t":1035,"safe_x":154032,"safe_y":582463,"safe_r":67221,"warn_x":150183,"warn_y":561919,"warn_r":36971},{"t":1045,"safe_x":154032,"safe_y":582463,"safe_r":67221,"warn_x":150183,"warn_y":561919,"warn_r":36971},{"t":1055,"safe_x":154032,"safe_y":582463,"safe_r":67221,"warn_x":150183,"warn_y":561919,"warn_r":36971},{"t":1065,"safe_x":154032,"safe_y":582463,"safe_r":67221,"warn_x":150183,"warn_y":561919,"warn_r":36971},{"t":1075,"safe_x":154032,"safe_y":582463,"safe_r":67221,"warn_x":150183,"warn_y":561919,"warn_r":36971},{"t":1085,"safe_x":153555,"safe_y":579920,"safe_r":63476,"warn_x":150183,"warn_y":561919,"warn_r":36971},{"t":1095,"safe_x":153075,"safe_y":577356,"safe_r":59700,"warn_x":150183,"warn_y":561919,"warn_r":36971},{"t":1105,"safe_x":152593,"safe_y":574784,"safe_r":55914,"warn_x":150183,"warn_y":561919,"warn_r":36971},{"t":1115,"safe_x":152112,"safe_y":572214,"safe_r":52129,"warn_x":150183,"warn_y":561919,"warn_r":36971},{"t":1125,"safe_x":151629,"safe_y":569636,"safe_r":48334,"warn_x":150183,"warn_y":561919,"warn_r":36971},{"t":1135,"safe_x":151147,"safe_y":567063,"safe_r":44546,"warn_x":150183,"warn_y":561919,"warn_r":36971},{"t":1145,"safe_x":150667,"safe_y":564499,"safe_r":40770,"warn_x":150183,"warn_y":561919,"warn_r":36971},{"t":1155,"safe_x":150185,"safe_y":561928,"safe_r":36985,"warn_x":150183,"warn_y":561919,"warn_r":36971},{"t":1165,"safe_x":150183,"safe_y":561919,"safe_r":36971,"warn_x":131968,"warn_y":559194,"warn_r":18486},{"t":1175,"safe_x":150183,"safe_y":561919,"safe_r":36971,"warn_x":131968,"warn_y":559194,"warn_r":18486},{"t":1185,"safe_x":150183,"safe_y":561919,"safe_r":36971,"warn_x":131968,"warn_y":559194,"warn_r":18486},{"t":1195,"safe_x":150183,"safe_y":561919,"safe_r":36971,"warn_x":131968,"warn_y":559194,"warn_r":18486},{"t":1205,"safe_x":150183,"safe_y":561919,"safe_r":36971,"warn_x":131968,"warn_y":559194,"warn_r":18486},{"t":1215,"safe_x":150183,"safe_y":561919,"safe_r":36971,"warn_x":131968,"warn_y":559194,"warn_r":18486},{"t":1225,"safe_x":150183,"safe_y":561919,"safe_r":36971,"warn_x":131968,"warn_y":559194,"warn_r":18486},{"t":1235,"safe_x":150183,"safe_y":561919,"safe_r":36971,"warn_x":131968,"warn_y":559194,"warn_r":18486},{"t":1245,"safe_x":150183,"safe_y":561919,"safe_r":36971,"warn_x":131968,"warn_y":559194,"warn_r":18486},{"t":1255,"safe_x":150153,"safe_y":561915,"safe_r":36940,"warn_x":131968,"warn_y":559194,"warn_r":18486},{"t":1265,"safe_x":147107,"safe_y":561459,"safe_r":33849,"warn_x":131968,"warn_y":559194,"warn_r":18486},{"t":1275,"safe_x":144071,"safe_y":561005,"safe_r":30768,"warn_x":131968,"warn_y":559194,"warn_r":18486},{"t":1285,"safe_x":141030,"safe_y":560550,"safe_r":27682,"warn_x":131968,"warn_y":559194,"warn_r":18486},{"t":1294,"safe_x":137994,"safe_y":560095,"safe_r":24601,"warn_x":131968,"warn_y":559194,"warn_r":18486},{"t":1304,"safe_x":134953,"safe_y":559640,"safe_r":21515,"warn_x":131968,"warn_y":559194,"warn_r":18486},{"t":1314,"safe_x":131968,"safe_y":559194,"safe_r":18486,"warn_x":131633,"warn_y":563517,"warn_r":9243},{"t":1324,"safe_x":131968,"safe_y":559194,"safe_r":18486,"warn_x":131633,"warn_y":563517,"warn_r":9243},{"t":1334,"safe_x":131968,"safe_y":559194,"safe_r":18486,"warn_x":131633,"warn_y":563517,"warn_r":9243},{"t":1344,"safe_x":131968,"safe_y":559194,"safe_r":18486,"warn_x":131633,"warn_y":563517,"warn_r":9243},{"t":1354,"safe_x":131968,"safe_y":559194,"safe_r":18486,"warn_x":131633,"warn_y":563517,"warn_r":9243},{"t":1364,"safe_x":131968,"safe_y":559194,"safe_r":18486,"warn_x":131633,"warn_y":563517,"warn_r":9243},{"t":1374,"safe_x":131968,"safe_y":559194,"safe_r":18486,"warn_x":131633,"warn_y":563517,"warn_r":9243}],"events":[{"type":"dmg_taken","t":77.8,"player":"S821","x":217922,"y":397452,"damage":39.9,"weapon":"SCAR-L","reason":"TorsoShot","attacker":"CorkyCorc"},{"type":"dmg_taken","t":78.1,"player":"S821","x":218045,"y":397483,"damage":22.7,"weapon":"SCAR-L","reason":"ArmShot","attacker":"CorkyCorc"},{"type":"dmg_taken","t":78.1,"player":"S821","x":218113,"y":397498,"damage":22.7,"weapon":"SCAR-L","reason":"ArmShot","attacker":"CorkyCorc"},{"type":"dmg_taken","t":78.3,"player":"S821","x":218171,"y":397509,"damage":14.7,"weapon":"SCAR-L","reason":"ArmShot","attacker":"CorkyCorc"},{"type":"knocked","t":78.3,"player":"S821","x":218171,"y":397509,"attacker":"CorkyCorc"},{"type":"throwable","t":78.9,"player":"D282","x":216245,"y":394432,"weapon":"Grenade"},{"type":"dmg_taken","t":117.5,"player":"D282","x":216043,"y":393292,"damage":42,"weapon":"SCAR-L","reason":"TorsoShot","attacker":"CorkyCorc"},{"type":"dmg_taken","t":117.6,"player":"D282","x":216035,"y":393291,"damage":42,"weapon":"SCAR-L","reason":"TorsoShot","attacker":"CorkyCorc"},{"type":"dmg_taken","t":117.6,"player":"D282","x":216031,"y":393291,"damage":16,"weapon":"SCAR-L","reason":"HeadShot","attacker":"CorkyCorc"},{"type":"death","t":117.7,"player":"S821","x":218839,"y":397341,"killer":"CorkyCorc","weapon":"SCAR-L"},{"type":"death","t":117.7,"player":"D282","x":216031,"y":393291,"killer":"CorkyCorc","weapon":"SCAR-L"}]}